dpg_pages/__init__.py
dpg_pages/dpg_pages.py
dpg_pages-0.2.0.dist-info/licenses/LICENSE
dpg_pages-0.2.0.dist-info/METADATA
dpg_pages-0.2.0.dist-info/WHEEL
dpg_pages-0.2.0.dist-info/top_level.txt
dpg_pages-0.2.0.dist-info/RECORD
