Metadata-Version: 2.4
Name: dpg-pages
Version: 0.2.0
Summary: A simple page system for DearPyGui.
Author-email: Rostyslav Nikolenko <rostislavnikolenkowork@gmail.com>
License: MIT License
License-File: LICENSE
Requires-Dist: dearpygui
Dynamic: license-file
